src/__init__.py
src/constants.py
src/printing.py
src/prompt.py
src/subsheets.py
subsheets-0.8.dist-info/LICENSE
subsheets-0.8.dist-info/METADATA
subsheets-0.8.dist-info/WHEEL
subsheets-0.8.dist-info/entry_points.txt
subsheets-0.8.dist-info/top_level.txt
subsheets-0.8.dist-info/RECORD
