Metadata-Version: 2.1
Name: subsheets
Version: 0.8
Summary: utility to create subsheets in excel file
Home-page: https://github.com/CruiseDevice/subsheets
Author: Akash Chavan
Author-email: achavan1211@gmail.com
License: UNKNOWN
Keywords: subsheets sheets
Platform: UNKNOWN
Classifier: Programming Language :: Python :: 3
Classifier: License :: OSI Approved :: MIT License
Classifier: Operating System :: OS Independent
Requires-Python: >=3.6
Requires-Dist: pandas
Requires-Dist: xlrd
Requires-Dist: XlsxWriter
Requires-Dist: Click
Requires-Dist: colorama
Requires-Dist: inquirer
